pearl/Pearl.py
pearl/__init__.py
pearl/agent.py
pearl/build_and_publish.py
pearl/env.py
pearl/mask.py
pearl/method.py
pearl/setup.py
pearl/test_package.py
pearl/agents/SimpleDQN.py
pearl/agents/TorchPolicy.py
pearl/agents/TourchDQN.py
pearl/enviroments/GymRLEnv.py
pearl/enviroments/ObservationWrapper.py
pearl/methods/LMUTExplainability.py
pearl/methods/LimeExplainability.py
pearl/methods/ShapExplainability.py
pearl/methods/Stability.py
pearl/methods/TabularLimeExplainability.py
pearl/provided/AssaultEnv.py
pearl/provided/LunarLander.py
pearl_rl-0.1.2.dist-info/licenses/LICENSE
pearl_rl-0.1.2.dist-info/METADATA
pearl_rl-0.1.2.dist-info/WHEEL
pearl_rl-0.1.2.dist-info/top_level.txt
pearl_rl-0.1.2.dist-info/RECORD
