Metadata-Version: 2.4
Name: pearl-rl
Version: 0.1.2
Summary: A reinforcement learning model selection library using explainability
Home-page: https://github.com/P-E-A-R-L/Pearl
Author: Youssef Rabie & Abdelrahman Mohamed Mahmoud Sobhy & Youssef Hagag
Author-email: Youssef Rabie & Abdelrahman Mohamed Mahmoud Sobhy & Youssef Hagag <yousef.mohamed.rabia@gmail.com>
Maintainer-email: Youssef Rabie & Abdelrahman Mohamed Mahmoud Sobhy & Youssef Hagag <yousef.mohamed.rabia@gmail.com>
License: MIT
Project-URL: Homepage, https://github.com/P-E-A-R-L/Pearl
Project-URL: Documentation, https://github.com/P-E-A-R-L/Pearl#readme
Project-URL: Repository, https://github.com/P-E-A-R-L/Pearl.git
Project-URL: Bug Tracker, https://github.com/P-E-A-R-L/Pearl/issues
Keywords: reinforcement-learning,machine-learning,explainability,ai,rl,model-selection
Classifier: Development Status :: 3 - Alpha
Classifier: Intended Audience :: Developers
Classifier: Intended Audience :: Science/Research
Classifier: License :: OSI Approved :: MIT License
Classifier: Operating System :: OS Independent
Classifier: Programming Language :: Python :: 3
Classifier: Programming Language :: Python :: 3.8
Classifier: Programming Language :: Python :: 3.9
Classifier: Programming Language :: Python :: 3.10
Classifier: Programming Language :: Python :: 3.11
Classifier: Topic :: Scientific/Engineering :: Artificial Intelligence
Classifier: Topic :: Software Development :: Libraries :: Python Modules
Requires-Python: >=3.8
License-File: LICENSE
Requires-Dist: numpy>=1.21.0
Requires-Dist: torch>=1.9.0
Requires-Dist: gymnasium>=0.26.0
Requires-Dist: matplotlib>=3.5.0
Requires-Dist: stable-baselines3>=1.5.0
Requires-Dist: opencv-python>=4.5.0
Requires-Dist: pandas>=1.3.0
Requires-Dist: tqdm>=4.62.0
Requires-Dist: tensorboard>=2.8.0
Provides-Extra: dev
Requires-Dist: pytest>=6.0; extra == "dev"
Requires-Dist: pytest-cov>=2.0; extra == "dev"
Requires-Dist: black>=21.0; extra == "dev"
Requires-Dist: flake8>=3.8; extra == "dev"
Requires-Dist: mypy>=0.800; extra == "dev"
Requires-Dist: pre-commit>=2.15.0; extra == "dev"
Dynamic: author
Dynamic: home-page
Dynamic: license-file
Dynamic: requires-python
